pandas_path/__init__.py
pandas_path/accessor.py
pandas_path/tests.py
pandas_path/path/__init__.py
pandas_path-0.3.0.dist-info/LICENSE.txt
pandas_path-0.3.0.dist-info/METADATA
pandas_path-0.3.0.dist-info/WHEEL
pandas_path-0.3.0.dist-info/top_level.txt
pandas_path-0.3.0.dist-info/RECORD
