Metadata-Version: 2.1
Name: pandas-path
Version: 0.3.0
Summary: Pathlib functionality for pandas.
Home-page: https://github.com/drivendataorg/pandas-path
Author: DrivenData
Author-email: info@drivendata.org
License: MIT
Project-URL: Source Code, https://github.com/drivendataorg/pandas-path
Project-URL: DrivenData, http://drivendata.co
Keywords: data science
Platform: UNKNOWN
Classifier: Programming Language :: Python
Classifier: Programming Language :: Python :: 3
Classifier: Programming Language :: Python :: 3.6
Classifier: Intended Audience :: Developers
Classifier: Intended Audience :: Science/Research
Classifier: License :: OSI Approved :: MIT License
Classifier: Topic :: Scientific/Engineering
Classifier: Topic :: Scientific/Engineering :: Artificial Intelligence
Requires-Python: >=3.6
Requires-Dist: pandas (>=0.23)
Requires-Dist: importlib-metadata ; python_version < "3.8"
